<?xml version="1.0" encoding="utf-8"?>
<CoverageReport scope="Summary">
  <Summary>
    <Generatedon>10/04/2021 - 12:20:43</Generatedon>
    <Parser>MultiReportParser (2x OpenCoverParser)</Parser>
    <Assemblies>1</Assemblies>
    <Classes>5</Classes>
    <Files>5</Files>
    <Coveredlines>99</Coveredlines>
    <Uncoveredlines>0</Uncoveredlines>
    <Coverablelines>99</Coverablelines>
    <Totallines>234</Totallines>
    <Linecoverage>100</Linecoverage>
    <Coveredbranches>0</Coveredbranches>
    <Totalbranches>0</Totalbranches>
  </Summary>
  <Coverage>
    <Assembly name="Aloha" classes="5" coverage="100" coveredlines="99" coverablelines="99" totallines="234" branchcoverage="" coveredbranches="0" totalbranches="0">
      <Class name="Aloha.BasicTile" coverage="100" coveredlines="6" coverablelines="6" totallines="22" branchcoverage="" coveredbranches="0" totalbranches="0" />
      <Class name="Aloha.Enemy" coverage="100" coveredlines="16" coverablelines="16" totallines="38" branchcoverage="" coveredbranches="0" totalbranches="0" />
      <Class name="Aloha.EnemyInstantier" coverage="100" coveredlines="8" coverablelines="8" totallines="30" branchcoverage="" coveredbranches="0" totalbranches="0" />
      <Class name="Aloha.TilesManager" coverage="100" coveredlines="53" coverablelines="53" totallines="100" branchcoverage="" coveredbranches="0" totalbranches="0" />
      <Class name="Singleton[T]" coverage="100" coveredlines="16" coverablelines="16" totallines="44" branchcoverage="" coveredbranches="0" totalbranches="0" />
    </Assembly>
  </Coverage>
</CoverageReport>